Metadata-Version: 1.0
Name: distribution-Gauss
Version: 0.1.0
Summary: Gaussian distributions
Home-page: UNKNOWN
Author: Pongrak Keawsrinuan
Author-email: pongrak.k@hotmail.com
License: UNKNOWN
Platform: UNKNOWN
